open_bedrock_server/__init__.py
open_bedrock_server/_version.py
open_bedrock_server/adapters/__init__.py
open_bedrock_server/adapters/base_adapter.py
open_bedrock_server/adapters/bedrock_to_openai_adapter.py
open_bedrock_server/adapters/openai_adapter.py
open_bedrock_server/adapters/bedrock/__init__.py
open_bedrock_server/adapters/bedrock/ai21_strategy.py
open_bedrock_server/adapters/bedrock/bedrock_adapter.py
open_bedrock_server/adapters/bedrock/bedrock_adapter_strategy_abc.py
open_bedrock_server/adapters/bedrock/bedrock_models.py
open_bedrock_server/adapters/bedrock/claude_strategy.py
open_bedrock_server/adapters/bedrock/cohere_strategy.py
open_bedrock_server/adapters/bedrock/meta_strategy.py
open_bedrock_server/adapters/bedrock/mistral_strategy.py
open_bedrock_server/adapters/bedrock/nova_strategy.py
open_bedrock_server/adapters/bedrock/stability_strategy.py
open_bedrock_server/adapters/bedrock/titan_strategy.py
open_bedrock_server/adapters/bedrock/writer_strategy.py
open_bedrock_server/api/__init__.py
open_bedrock_server/api/app.py
open_bedrock_server/api/errors.py
open_bedrock_server/api/middleware/__init__.py
open_bedrock_server/api/middleware/auth.py
open_bedrock_server/api/middleware/logging.py
open_bedrock_server/api/routes/__init__.py
open_bedrock_server/api/routes/chat.py
open_bedrock_server/api/routes/files.py
open_bedrock_server/api/routes/health.py
open_bedrock_server/api/routes/knowledge_bases.py
open_bedrock_server/api/routes/models.py
open_bedrock_server/api/schemas/__init__.py
open_bedrock_server/api/schemas/file_schemas.py
open_bedrock_server/api/schemas/requests.py
open_bedrock_server/api/schemas/responses.py
open_bedrock_server/cli/__init__.py
open_bedrock_server/cli/chat_history.py
open_bedrock_server/cli/error_handling.py
open_bedrock_server/cli/formatters.py
open_bedrock_server/cli/main.py
open_bedrock_server/core/__init__.py
open_bedrock_server/core/bedrock_models.py
open_bedrock_server/core/exceptions.py
open_bedrock_server-2.0.4.dist-info/licenses/LICENSE
open_bedrock_server-2.0.4.dist-info/METADATA
open_bedrock_server-2.0.4.dist-info/WHEEL
open_bedrock_server-2.0.4.dist-info/entry_points.txt
open_bedrock_server-2.0.4.dist-info/top_level.txt
open_bedrock_server-2.0.4.dist-info/RECORD
