Metadata-Version: 2.4
Name: open-bedrock-server
Version: 2.0.4
Summary: A unified, provider-agnostic chat completions API server that seamlessly integrates OpenAI and AWS Bedrock through a single endpoint with intelligent format detection and conversion.
Author-email: teabranch <teller@tipalti.com>
Maintainer-email: teabranch <teller@tipalti.com>
License-Expression: MIT
Project-URL: Homepage, https://github.com/teabranch/open-bedrock-server
Project-URL: Bug Tracker, https://github.com/teabranch/open-bedrock-server/issues
Project-URL: Documentation, https://github.com/teabranch/open-bedrock-server#readme
Keywords: aws,bedrock,openai,api,chat,completions,llm,ai
Classifier: Development Status :: 4 - Beta
Classifier: Intended Audience :: Developers
Classifier: Operating System :: OS Independent
Classifier: Programming Language :: Python :: 3
Classifier: Programming Language :: Python :: 3.9
Classifier: Programming Language :: Python :: 3.10
Classifier: Programming Language :: Python :: 3.11
Classifier: Programming Language :: Python :: 3.12
Requires-Python: >=3.9
License-File: LICENSE
Requires-Dist: fastapi>=0.104.1
Requires-Dist: pydantic>=2.5.0
Requires-Dist: uvicorn[standard]>=0.24.0
Requires-Dist: boto3>=1.34.0
Requires-Dist: click>=8.1.7
Requires-Dist: aiofiles>=23.2.1
Requires-Dist: python-multipart>=0.0.6
Requires-Dist: openai>=1.3.0
Requires-Dist: colorama>=0.4.6
Requires-Dist: rich>=13.7.0
Requires-Dist: python-dotenv>=1.0.0
Requires-Dist: httpx>=0.25.2
Requires-Dist: pillow>=10.1.0
Requires-Dist: python-magic>=0.4.27
Requires-Dist: pypdf2>=3.0.1
Requires-Dist: python-docx>=1.1.0
Requires-Dist: openpyxl>=3.1.2
Requires-Dist: pydantic-settings>=2.1.0
Requires-Dist: markdown>=3.5.1
Requires-Dist: jinja2>=3.1.2
Requires-Dist: requests>=2.25.0
Requires-Dist: tenacity>=8.2.0
Provides-Extra: dev
Requires-Dist: pytest>=7.4.3; extra == "dev"
Requires-Dist: pytest-asyncio>=0.21.1; extra == "dev"
Requires-Dist: pytest-cov>=4.1.0; extra == "dev"
Requires-Dist: black>=23.11.0; extra == "dev"
Requires-Dist: isort>=5.12.0; extra == "dev"
Requires-Dist: mypy>=1.7.1; extra == "dev"
Requires-Dist: flake8>=6.1.0; extra == "dev"
Requires-Dist: pre-commit>=3.6.0; extra == "dev"
Dynamic: license-file
